ripple_api/__init__.py
ripple_api/data_api.py
ripple_api/json_rpc.py
ripple_api/utils.py
python_ripple_lib-1.0.11.dist-info/LICENSE
python_ripple_lib-1.0.11.dist-info/METADATA
python_ripple_lib-1.0.11.dist-info/WHEEL
python_ripple_lib-1.0.11.dist-info/top_level.txt
python_ripple_lib-1.0.11.dist-info/RECORD
