Metadata-Version: 2.1
Name: python-ripple-lib
Version: 1.0.11
Summary: Ripple JSON-RPC API and Data API wrapper for Python
Home-page: https://github.com/arsenlosenko/python-ripple-lib
Author: Arsen Losenko
Author-email: arsenlosenko@protonmail.com
License: MIT
Keywords: ripple rippled json-rpc
Platform: UNKNOWN
Classifier: Development Status :: 3 - Alpha
Classifier: Intended Audience :: Developers
Classifier: Topic :: Utilities
Classifier: License :: OSI Approved :: MIT License
Classifier: Programming Language :: Python :: 3.6
